chkelastic/__init__.py
chkelastic/__main__.py
chkelastic/commands.py
chkelastic/connection.py
chkelastic/util.py
chkelastic-0.1.0.dist-info/METADATA
chkelastic-0.1.0.dist-info/WHEEL
chkelastic-0.1.0.dist-info/entry_points.txt
chkelastic-0.1.0.dist-info/top_level.txt
chkelastic-0.1.0.dist-info/RECORD
